LICENSE
MANIFEST.in
README.md
meson.build
pyproject.toml
setup.py
include/cdfbli.hpp
include/lognormal.hpp
include/math.hpp
pybalonor/__init__.py
pybalonor/bayes.pyx
pybalonor/posterior.py
pybalonor.egg-info/PKG-INFO
pybalonor.egg-info/SOURCES.txt
pybalonor.egg-info/dependency_links.txt
pybalonor.egg-info/requires.txt
pybalonor.egg-info/top_level.txt
pybalonor/prior/__init__.py
pybalonor/prior/flat.py
pybalonor/prior/prior.py
src/lognormal.cpp
src/math.cpp