Metadata-Version: 2.1
Name: pybalonor
Version: 1.0.0
Summary: Bayesian analysis of the log-normal distribution.
Author-email: "Malte J. Ziebarth" <mjz.science@fmvkb.de>
License:                       EUROPEAN UNION PUBLIC LICENCE v. 1.2
Project-URL: Homepage, https://github.com/mjziebarth/pybalonor
Project-URL: Bug Tracker, https://github.com/mjziebarth/pybalonor/issues
Project-URL: Documentation, https://mjziebarth.github.io/pybalonor/index.html
Classifier: Development Status :: 4 - Beta
Classifier: Programming Language :: Python :: 3
Classifier: Programming Language :: Cython
Classifier: Programming Language :: C++
Classifier: License :: OSI Approved :: European Union Public Licence 1.2 (EUPL 1.2)
Classifier: Intended Audience :: Science/Research
Classifier: Natural Language :: English
Classifier: Operating System :: POSIX :: Linux
Classifier: Topic :: Scientific/Engineering :: Mathematics
License-File: LICENSE
